ssm_dotenv/__init__.py
ssm_dotenv/cli.py
ssm_dotenv/errors.py
ssm_dotenv/params.py
ssm_dotenv-0.1.0.dist-info/LICENSE
ssm_dotenv-0.1.0.dist-info/METADATA
ssm_dotenv-0.1.0.dist-info/WHEEL
ssm_dotenv-0.1.0.dist-info/entry_points.txt
ssm_dotenv-0.1.0.dist-info/top_level.txt
ssm_dotenv-0.1.0.dist-info/RECORD
